<?xml version="1.0" encoding="UTF-8"?>
<databaseChangeLog
        xmlns="http://www.liquibase.org/xml/ns/dbchangelog"
        xmlns:xsi="http://www.w3.org/2001/XMLSchema-instance"
        xsi:schemaLocation="http://www.liquibase.org/xml/ns/dbchangelog
                      http://www.liquibase.org/xml/ns/dbchangelog/dbchangelog-3.1.xsd">

    <changeSet id="1" author="Vladislav">
        <createTable tableName="roles">
            <column name="id" type="integer" autoIncrement="true">
                <constraints primaryKey="true" nullable="false"/>
            </column>
            <column name="value" type="varchar(200)">
                <constraints nullable="false" unique="true"/>
            </column>
        </createTable>
    </changeSet>

    <changeSet id="2" author="Vladislav">
        <createTable tableName="user_roles">
            <column name="user_id" type="integer"/>
            <column name="roles_id" type="integer"/>
        </createTable>

        <addForeignKeyConstraint baseTableName="user_roles" baseColumnNames="user_id"
                                 constraintName="user_id_fk" referencedTableName="users"
                                 referencedColumnNames="id"/>

        <addForeignKeyConstraint baseTableName="user_roles" baseColumnNames="roles_id"
                                 constraintName="roles_id_fk" referencedTableName="roles"
                                 referencedColumnNames="id"/>

    </changeSet>


</databaseChangeLog>